{
  "type": "minecraft:simple_block",
  "config": {
    "to_place": {
      "type": "minecraft:weighted_state_provider",
      "entries": [
        {
          "data": {
            "Name": "aether_redux:cloudcap_mushling"
          },
          "weight": 40
        },
        {
          "data": {
            "Name": "aether_redux:jellyshroom"
          },
          "weight": 20
        },
        {
          "data": {
            "Name": "aether_redux:shimmerstool"
          },
          "weight": 15
        },
        {
          "data": {
            "Name": "aether_redux:fungal_carpet",
            "Properties": {
              "double_drops": "true"
            }
          },
          "weight": 75
        },
        {
          "data": {
            "Name": "aether_redux:avelium_sprouts"
          },
          "weight": 150
        },
        {
          "data": {
            "Name": "aether_redux:avelium_roots"
          },
          "weight": 120
        }
      ]
    }
  }
}