{
  "type": "aether_redux:raw_ore",
  "added_item": {
    "Count": 1,
    "id": "aether_redux:raw_valkyrum"
  },
  "conditions": [
    {
      "condition": "aether_redux:data_loot_condition",
      "data_loot_condition": {
        "arg1": {
          "condition": "aether_redux:redux_config",
          "config_path": "[Gameplay Changes, Raw Ores]"
        },
        "arg2": {
          "condition": "aether_redux:mod_loaded",
          "mod_id": "ancient_aether"
        },
        "condition": "aether_redux:and"
      }
    },
    {
      "condition": "minecraft:inverted",
      "term": {
        "condition": "minecraft:match_tool",
        "predicate": {
          "enchantments": [
            {
              "enchantment": "minecraft:silk_touch",
              "levels": {
                "min": 1
              }
            }
          ]
        }
      }
    },
    {
      "block": "ancient_aether:valkyrum_block",
      "condition": "minecraft:block_state_property"
    }
  ],
  "functions": [
    {
      "add": false,
      "count": 1.0,
      "function": "minecraft:set_count"
    },
    {
      "enchantment": "minecraft:fortune",
      "formula": "minecraft:ore_drops",
      "function": "minecraft:apply_bonus"
    }
  ],
  "item": "ancient_aether:valkyrum_block"
}